{
    "name": "Maria Monchot",

    "status": "Desarrolladora Web Full Stack Junior",

    "github": "https://github.com/KateClysm",

    "stack_overflow": "https://stackoverflow.com/users/20352686/maria-monchot",

    "linked_in": "https://ar.linkedin.com/in/maria-monchot?trk=public_profile_samename-profile",

    "education":[
        {
            "name": "Bachillerato en Comunicación",
            "mediante": "Presencialidad",
            "periodo": "00/00/0000--00/00/0000",
            "detalle":"Lorem"
        },

        {
            "name": "Tecnicatura Analista Programador Universitario",
            "mediante": "Presencialidad",
            "periodo": "00/00/0000--00/00/0000",
            "detalle":"Lorem"
        },

        {
            "name": "Plan Programar Argentina",
            "mediante": "Virtualidad",
            "periodo": "00/00/0000--00/00/0000",
            "detalle":"Lorem"
        }
    ],


    "proyectos":[
        {  
            "image":"Lorem", 
            "name": "Portfolio Web",
            "detalle": "Lorem",
            "creacion": "00/00/2022",
            "codigo": "https....",
            "ver_proyecto": "https..."
        },
        
        {
            "image":"Lorem",
            "name": "Online Game",
            "detalle": "Lorem2",
            "creacion": "00/00/2022",
            "codigo": "https....2",
            "ver_proyecto": "https...2"
        },

        {
            "image":"Lorem",
            "name": "Silly red neuronal",
            "detalle": "Lorem3",
            "creacion": "00/00/2023",
            "codigo": "https....3",
            "ver_proyecto": "https...3"
        }
    ],

    "experiencia":[
        {
            "logo":"https://i.pinimg.com/originals/07/1b/f3/071bf3e80bc7c664a74cbef1a8704a9b.png",
            "empresa": "Lorem Ipsum1",
            "cargo": "Lorem impsum dolor de lamentum1",
            "periodo": "00/00/0000--00/00/00001",
            "detalle": "Lorem impsum dolor de lamentum1"
        },

        {
            "logo":"https://uvn-brightspot.s3.amazonaws.com/assets/vixes/btg/cine.batanga.com/files/Los-15-mejores-logos-de-equipos-y-empresas-ficticias-en-el-cine-4.png",
            "empresa": "Monster Inc",
            "cargo": "Lorem impsum dolor de lamentum2",
            "periodo": "00/00/0000--00/00/00002",
            "detalle": "Lorem Lorem Lorem Lorem Lorem Lorem Lorem Lorem Lorem Lorem"
        },

        {
            "logo":"https://miratel.net/wp-content/uploads/2016/04/marcasficticias.jpg",
            "empresa": "Lorem Ipsum3",
            "cargo": "Lorem impsum dolor de lamentum3",
            "periodo": "00/00/0000--00/00/00031",
            "detalle": "Lorem impsum dolor de lamentum3"
        }
    ]

}